<?xml version="1.0" encoding="UTF-8"?>

<uicfg desc="按钮">
	<items>-></items>
	<items>
		<text>新增</text>
		<iconCls>create-icon</iconCls>
		<handler type="object">this.addClick</handler>
	</items>
	<items>
		<text>编辑</text>
		<iconCls>new-edit-icon</iconCls>
		<handler type="object">this.editClick</handler>
	</items>
	<items>
		<text>删除</text>
		<iconCls>delete-selected-icon</iconCls>
		<handler type="object">this.deleteClick</handler>
	</items>
	<items>
		<text>查看</text>
		<iconCls>view-icon</iconCls>
		<handler type="object">this.viewClick</handler>
	</items>
	<items>
		<text>查询</text>
		<iconCls>search-d-icon</iconCls>
		<handler type="object">this.query</handler>
	</items>
	<items>
		<text>清空</text>
		<iconCls>ff-clear-icon</iconCls>
		<handler type="object">this.clear</handler>
	</items>
	<items>
		<tooltip>展开/收起查询区</tooltip>
		<iconCls>collapse-icon</iconCls>
		<handler type="object">this.expandQueryField</handler>
	</items>
</uicfg>
